{
  "/(public)/page": "app/(public)/page.js",
  "/(public)/products/[slug]/page": "app/(public)/products/[slug]/page.js",
  "/(public)/products/page": "app/(public)/products/page.js",
  "/_global-error/page": "app/_global-error/page.js",
  "/_not-found/page": "app/_not-found/page.js",
  "/admin/(dashboard)/audit-logs/page": "app/admin/(dashboard)/audit-logs/page.js",
  "/admin/(dashboard)/brands/[id]/edit/page": "app/admin/(dashboard)/brands/[id]/edit/page.js",
  "/admin/(dashboard)/brands/new/page": "app/admin/(dashboard)/brands/new/page.js",
  "/admin/(dashboard)/brands/page": "app/admin/(dashboard)/brands/page.js",
  "/admin/(dashboard)/categories/[id]/edit/page": "app/admin/(dashboard)/categories/[id]/edit/page.js",
  "/admin/(dashboard)/categories/new/page": "app/admin/(dashboard)/categories/new/page.js",
  "/admin/(dashboard)/categories/page": "app/admin/(dashboard)/categories/page.js",
  "/admin/(dashboard)/media/page": "app/admin/(dashboard)/media/page.js",
  "/admin/(dashboard)/page": "app/admin/(dashboard)/page.js",
  "/admin/(dashboard)/portfolios/[id]/edit/page": "app/admin/(dashboard)/portfolios/[id]/edit/page.js",
  "/admin/(dashboard)/portfolios/new/page": "app/admin/(dashboard)/portfolios/new/page.js",
  "/admin/(dashboard)/portfolios/page": "app/admin/(dashboard)/portfolios/page.js",
  "/admin/(dashboard)/products/[id]/edit/page": "app/admin/(dashboard)/products/[id]/edit/page.js",
  "/admin/(dashboard)/products/new/page": "app/admin/(dashboard)/products/new/page.js",
  "/admin/(dashboard)/products/page": "app/admin/(dashboard)/products/page.js",
  "/admin/(dashboard)/roles/[id]/edit/page": "app/admin/(dashboard)/roles/[id]/edit/page.js",
  "/admin/(dashboard)/roles/new/page": "app/admin/(dashboard)/roles/new/page.js",
  "/admin/(dashboard)/roles/page": "app/admin/(dashboard)/roles/page.js",
  "/admin/(dashboard)/users/[id]/edit/page": "app/admin/(dashboard)/users/[id]/edit/page.js",
  "/admin/(dashboard)/users/new/page": "app/admin/(dashboard)/users/new/page.js",
  "/admin/(dashboard)/users/page": "app/admin/(dashboard)/users/page.js",
  "/admin/login/page": "app/admin/login/page.js",
  "/api/media/upload/route": "app/api/media/upload/route.js",
  "/api/webhooks/mux/route": "app/api/webhooks/mux/route.js"
}